aiohttp_extracts/__init__.py
aiohttp_extracts-0.0.1a1.dist-info/LICENSE
aiohttp_extracts-0.0.1a1.dist-info/METADATA
aiohttp_extracts-0.0.1a1.dist-info/WHEEL
aiohttp_extracts-0.0.1a1.dist-info/top_level.txt
aiohttp_extracts-0.0.1a1.dist-info/RECORD
