Metadata-Version: 2.1
Name: aiohttp-extracts
Version: 0.0.1a1
Summary: Sugar library for aiohttp handlers
Home-page: https://github.com/jorektheglitch/aiohttp-extracts
Author: jorektheglitch
Author-email: jorektheglitch@yandex.ru
License: UNKNOWN
Platform: UNKNOWN
Classifier: Programming Language :: Python :: 3
Classifier: Operating System :: OS Independent
Requires-Python: >=3.6
Requires-Dist: aiohttp
